iron_cage-0.2.0.dist-info/METADATA
iron_cage-0.2.0.dist-info/WHEEL
iron_cage.libs/libcrypto-83ee6b48.so.3
iron_cage.libs/libssl-c6703846.so.3
iron_cage/__init__.py
iron_cage/__init__.pyi
iron_cage/iron_cage.cpython-312-x86_64-linux-gnu.so
iron_cage/py.typed
iron_cage-0.2.0.dist-info/RECORD
