Metadata-Version: 2.4
Name: iron-cage
Version: 0.2.0
Classifier: Development Status :: 3 - Alpha
Classifier: Intended Audience :: Developers
Classifier: License :: OSI Approved :: MIT License
Classifier: Programming Language :: Rust
Classifier: Programming Language :: Python :: Implementation :: CPython
Classifier: Programming Language :: Python :: 3
Classifier: Programming Language :: Python :: 3.9
Classifier: Programming Language :: Python :: 3.10
Classifier: Programming Language :: Python :: 3.11
Classifier: Programming Language :: Python :: 3.12
Requires-Dist: pytest>=8.0.0 ; extra == 'dev'
Requires-Dist: pytest-asyncio>=0.24.0 ; extra == 'dev'
Requires-Dist: pytest-cov>=4.0.0 ; extra == 'dev'
Requires-Dist: black>=24.0.0 ; extra == 'dev'
Requires-Dist: mypy>=1.0.0 ; extra == 'dev'
Requires-Dist: ruff>=0.1.0 ; extra == 'dev'
Requires-Dist: langchain>=0.3.0 ; extra == 'examples'
Requires-Dist: langchain-community>=0.3.0 ; extra == 'examples'
Requires-Dist: langchain-openai>=0.2.0 ; extra == 'examples'
Requires-Dist: openai>=1.50.0 ; extra == 'examples'
Requires-Dist: typing-extensions>=4.12.0 ; extra == 'examples'
Requires-Dist: langchain>=0.1.0 ; extra == 'langchain'
Requires-Dist: crewai>=0.1.0 ; extra == 'crewai'
Requires-Dist: autogpt>=0.1.0 ; extra == 'autogpt'
Requires-Dist: langchain>=0.1.0 ; extra == 'all'
Requires-Dist: crewai>=0.1.0 ; extra == 'all'
Requires-Dist: autogpt>=0.1.0 ; extra == 'all'
Provides-Extra: dev
Provides-Extra: examples
Provides-Extra: langchain
Provides-Extra: crewai
Provides-Extra: autogpt
Provides-Extra: all
Summary: Iron SDK - Python SDK for AI agent protection with LLM proxy and safety controls
Author: Iron Cage Team
License: MIT
Requires-Python: >=3.9
